pymantra-1.0.2.dist-info/RECORD
pymantra-1.0.2.dist-info/LICENSE
pymantra-1.0.2.dist-info/WHEEL
pymantra-1.0.2.dist-info/top_level.txt
pymantra-1.0.2.dist-info/METADATA
pymantra/boost_available.cpp
pymantra/boost_version.cpp
pymantra/statics.py
pymantra/plotting.py
pymantra/datasets.py
pymantra/__init__.py
pymantra/database/query.py
pymantra/database/__init__.py
pymantra/database/utils.py
pymantra/database/exceptions.py
pymantra/database/APINetworkGenerator.py
pymantra/database/base.py
pymantra/namemapping/metaboanalyst_mapping.py
pymantra/namemapping/name_mapping.py
pymantra/namemapping/__init__.py
pymantra/namemapping/databases/__init__.py
pymantra/namemapping/databases/sqlite_base.py
pymantra/namemapping/databases/ChEBI/query.py
pymantra/namemapping/databases/ChEBI/chebi.db
pymantra/namemapping/databases/ChEBI/__init__.py
pymantra/namemapping/databases/ChEBI/reduce_columns.py
pymantra/namemapping/databases/HMDB/xml_processing.py
pymantra/namemapping/databases/HMDB/query.py
pymantra/namemapping/databases/HMDB/__init__.py
pymantra/namemapping/databases/HMDB/hmdb.db
pymantra/namemapping/databases/mantra_db/query.py
pymantra/namemapping/databases/mantra_db/__init__.py
pymantra/namemapping/databases/mantra_db/mantra.db
pymantra/namemapping/databases/Reactome/query.py
pymantra/namemapping/databases/Reactome/reactome.db
pymantra/namemapping/databases/Reactome/__init__.py
pymantra/network/enrichment_functions.py
pymantra/network/__init__.py
pymantra/network/io_estimation.py
pymantra/network/non_parametric_multivariate.py
pymantra/network/reaction_associations.py
pymantra/network/ld_estimation.py
pymantra/network/exceptions.py
pymantra/network/enrichment/statsutils.hpp
pymantra/network/enrichment/__init__.py
pymantra/network/enrichment/LocalSearch.py
pymantra/network/enrichment/spearman.cpython-38-darwin.so
pymantra/network/enrichment/LSO/LocalSearch.hpp
pymantra/network/enrichment/LSO/__init__.py
pymantra/network/enrichment/LSO/lso.cpython-38-darwin.so
pymantra/network/enrichment/LSO/reaction_graph.hpp
pymantra/data/example_graph.graphml
pymantra/data/example_graph_query.py
