Metadata-Version: 2.1
Name: pymantra
Version: 1.0.2
Summary: Reaction-Centred Metabolic Network Analysis
Author: Josch Konstantin Pauling
Author-email: Nikolai Koehler <nikolai.koehler@tum.de>
Maintainer: Josch Konstantin Pauling
Maintainer-email: Nikolai Koehler <nikolai.koehler@tum.de>
License: AGPLv3
Project-URL: Source, https://www.github.com/lipitum/pymantra
Project-URL: Documentation, https://pymantra.readthedocs.io
Project-URL: Publication, https://doi.org/10.1101/2023.05.15.540613
Keywords: Bioinformatics,Computational Metabolomics,Metabolic Network
Classifier: License :: OSI Approved :: GNU Affero General Public License v3
Classifier: Topic :: Scientific/Engineering :: Bio-Informatics
Classifier: Intended Audience :: Science/Research
Classifier: Natural Language :: English
Classifier: Operating System :: MacOS
Classifier: Operating System :: Microsoft :: Windows
Classifier: Operating System :: POSIX :: Linux
Classifier: Programming Language :: Python :: 3
License-File: LICENSE
Requires-Dist: pandas >=1.4.3
Requires-Dist: scipy >=1.8.0
Requires-Dist: scikit-learn >=1.0.2
Requires-Dist: networkx >=2.8.0
Requires-Dist: tqdm >=4.62.1
Requires-Dist: matplotlib >=3.3.0
Requires-Dist: seaborn >=0.9.0
Requires-Dist: neo4j >=4.4.0
Requires-Dist: pingouin >=0.5.2
Requires-Dist: statsmodels >=0.13.5
Requires-Dist: pandas-flavor
Requires-Dist: seaborn
Requires-Dist: outdated
Provides-Extra: dev
Requires-Dist: pytest ; extra == 'dev'
Requires-Dist: pytest-cov ; extra == 'dev'
Requires-Dist: flake8 ; extra == 'dev'
Requires-Dist: coverage ; extra == 'dev'
Provides-Extra: docs
Requires-Dist: Sphinx ; extra == 'docs'
Requires-Dist: furo ; extra == 'docs'
Requires-Dist: sphinxcontrib-bibtex ; extra == 'docs'
Requires-Dist: sphinx-copybutton ; extra == 'docs'
Requires-Dist: sphinxcontrib-mermaid >=0.8.1 ; extra == 'docs'
Provides-Extra: experiments
Requires-Dist: scikit-bio ; extra == 'experiments'
Requires-Dist: openpyxl ; extra == 'experiments'
Requires-Dist: scikit-optimize ; extra == 'experiments'
